PyProg/__init__.py
PyProg/manager.py
PyProg/ntbk_progbar.py
PyProg/ntbk_spinner.py
PyProg/progress_bar.py
PyProg/spinner.py
PyProg/utils.py
pyprog_abubakaransari-0.1.4.dist-info/licenses/LICENSE
pyprog_abubakaransari-0.1.4.dist-info/METADATA
pyprog_abubakaransari-0.1.4.dist-info/WHEEL
pyprog_abubakaransari-0.1.4.dist-info/top_level.txt
pyprog_abubakaransari-0.1.4.dist-info/RECORD
