Metadata-Version: 2.4
Name: pyprog-abubakaransari
Version: 0.1.4
Summary: Progress bars and spinners for terminal and notebooks
Author-email: Muhammad Abubakar Siddique Ansari <ansaricodes@gmail.com>
License: Apache-2.0
Classifier: Programming Language :: Python :: 3
Classifier: Operating System :: OS Independent
Requires-Python: >=3.7
License-File: LICENSE
Requires-Dist: IPython==8.12.3
Requires-Dist: colorama==0.4.6
Dynamic: license-file
